{
  "updated_at": "2026-04-12 06:10 UTC",
  "prices": [
    {
      "id": "bitcoin",
      "symbol": "BTC",
      "price": 71731,
      "change_24h": -1.343886307049522
    },
    {
      "id": "ethereum",
      "symbol": "ETH",
      "price": 2220.13,
      "change_24h": -0.6025996811802022
    },
    {
      "id": "binancecoin",
      "symbol": "BNB",
      "price": 595.97,
      "change_24h": -1.4972688377043968
    },
    {
      "id": "solana",
      "symbol": "SOL",
      "price": 82.43,
      "change_24h": -1.9176660653103097
    },
    {
      "id": "ripple",
      "symbol": "XRP",
      "price": 1.33,
      "change_24h": -1.082066842910257
    },
    {
      "id": "cardano",
      "symbol": "ADA",
      "price": 0.243172,
      "change_24h": -2.8635137706605627
    }
  ],
  "bullish": [
    {
      "name": "Toncoin",
      "symbol": "TON",
      "price": 1.43,
      "change_24h": 9.29164439428281
    },
    {
      "name": "JUST",
      "symbol": "JST",
      "price": 0.075539,
      "change_24h": 7.855910728711021
    },
    {
      "name": "Siren",
      "symbol": "SIREN",
      "price": 0.792387,
      "change_24h": 7.6963808951139745
    },
    {
      "name": "Worldcoin",
      "symbol": "WLD",
      "price": 0.289141,
      "change_24h": 2.7639989001724445
    },
    {
      "name": "Flare",
      "symbol": "FLR",
      "price": 0.00787042,
      "change_24h": 2.7456787802100204
    }
  ],
  "bearish": [
    {
      "name": "Rain",
      "symbol": "RAIN",
      "price": 0.00772634,
      "change_24h": -5.29657460717207
    },
    {
      "name": "Midnight",
      "symbol": "NIGHT",
      "price": 0.03922176,
      "change_24h": -4.270729694375327
    },
    {
      "name": "Dash",
      "symbol": "DASH",
      "price": 41.94,
      "change_24h": -4.114715850899958
    },
    {
      "name": "Polkadot",
      "symbol": "DOT",
      "price": 1.23,
      "change_24h": -4.037238174027072
    },
    {
      "name": "Zcash",
      "symbol": "ZEC",
      "price": 361.86,
      "change_24h": -3.885422916318852
    }
  ]
}